unitdoc/__init__.py
unitdoc-0.3.2.dist-info/LICENSE
unitdoc-0.3.2.dist-info/METADATA
unitdoc-0.3.2.dist-info/WHEEL
unitdoc-0.3.2.dist-info/top_level.txt
unitdoc-0.3.2.dist-info/RECORD
