Metadata-Version: 2.1
Name: unitdoc
Version: 0.3.2
Summary: Classes that describe physical objects with units and easy serialization.
Home-page: https://github.com/deniz195/unitdoc
Author: Deniz Bozyigit
Author-email: deniz195@gmail.com
License: MIT
Platform: UNKNOWN
Classifier: Development Status :: 4 - Beta
Classifier: Intended Audience :: Developers
Classifier: License :: OSI Approved :: MIT License
Classifier: Programming Language :: Python :: 3
Classifier: Programming Language :: Python :: 3.5
Classifier: Programming Language :: Python :: 3.6
Requires-Dist: attrs
Requires-Dist: cattrs
Requires-Dist: attr-descriptions (>=0.1.3)
Requires-Dist: ruamel.yaml
Requires-Dist: pint-mtools (>=0.12.3)
Requires-Dist: python-dateutil
